ma_confluence_cli/__init__.py
ma_confluence_cli/confluence_cli.py
ma_confluence_cli-1.0.0.dist-info/METADATA
ma_confluence_cli-1.0.0.dist-info/WHEEL
ma_confluence_cli-1.0.0.dist-info/entry_points.txt
ma_confluence_cli-1.0.0.dist-info/top_level.txt
ma_confluence_cli-1.0.0.dist-info/RECORD
